framekit/__init__.py
framekit/audio_element.py
framekit/default-font.ttf
framekit/frame_base.py
framekit/image_element.py
framekit/master_scene_element.py
framekit/scene_element.py
framekit/text_element.py
framekit/video_element.py
framekit-0.6.10.dist-info/METADATA
framekit-0.6.10.dist-info/WHEEL
framekit-0.6.10.dist-info/top_level.txt
framekit-0.6.10.dist-info/RECORD
