Metadata-Version: 2.4
Name: framekit
Version: 0.6.10
Requires-Python: >=3.12
Requires-Dist: moderngl
Requires-Dist: glcontext
Requires-Dist: av
Requires-Dist: freetype-py
Requires-Dist: Pillow
Requires-Dist: tqdm
Requires-Dist: numpy
